psemail/__init__.py
psemail/config.py
psemail/email_sender.py
psemail-1.2.dist-info/LICENSE
psemail-1.2.dist-info/METADATA
psemail-1.2.dist-info/WHEEL
psemail-1.2.dist-info/top_level.txt
psemail-1.2.dist-info/RECORD
