Metadata-Version: 2.1
Name: psemail
Version: 1.2
Summary: UNKNOWN
Home-page: https://github.com/LaythOud/psemail
License: UNKNOWN
Platform: UNKNOWN
Requires-Python: >=3.6
License-File: LICENSE
Requires-Dist: python-dotenv
